graphene/__init__.py
graphene/pyutils/__init__.py
graphene/pyutils/dataclasses.py
graphene/pyutils/version.py
graphene/relay/__init__.py
graphene/relay/connection.py
graphene/relay/mutation.py
graphene/relay/node.py
graphene/relay/tests/__init__.py
graphene/relay/tests/test_connection.py
graphene/relay/tests/test_connection_async.py
graphene/relay/tests/test_connection_query.py
graphene/relay/tests/test_global_id.py
graphene/relay/tests/test_mutation.py
graphene/relay/tests/test_mutation_async.py
graphene/relay/tests/test_node.py
graphene/relay/tests/test_node_custom.py
graphene/test/__init__.py
graphene/tests/__init__.py
graphene/tests/utils.py
graphene/tests/issues/__init__.py
graphene/tests/issues/test_313.py
graphene/tests/issues/test_356.py
graphene/tests/issues/test_425.py
graphene/tests/issues/test_490.py
graphene/tests/issues/test_720.py
graphene/tests/issues/test_956.py
graphene/types/__init__.py
graphene/types/argument.py
graphene/types/base.py
graphene/types/base64.py
graphene/types/context.py
graphene/types/datetime.py
graphene/types/decimal.py
graphene/types/definitions.py
graphene/types/dynamic.py
graphene/types/enum.py
graphene/types/field.py
graphene/types/generic.py
graphene/types/inputfield.py
graphene/types/inputobjecttype.py
graphene/types/interface.py
graphene/types/json.py
graphene/types/mountedtype.py
graphene/types/mutation.py
graphene/types/objecttype.py
graphene/types/resolver.py
graphene/types/scalars.py
graphene/types/schema.py
graphene/types/structures.py
graphene/types/union.py
graphene/types/unmountedtype.py
graphene/types/utils.py
graphene/types/uuid.py
graphene/types/tests/__init__.py
graphene/types/tests/test_argument.py
graphene/types/tests/test_base.py
graphene/types/tests/test_base64.py
graphene/types/tests/test_datetime.py
graphene/types/tests/test_decimal.py
graphene/types/tests/test_definition.py
graphene/types/tests/test_dynamic.py
graphene/types/tests/test_enum.py
graphene/types/tests/test_field.py
jetblack_graphene-3.0b5.dist-info/LICENSE
jetblack_graphene-3.0b5.dist-info/METADATA
jetblack_graphene-3.0b5.dist-info/WHEEL
jetblack_graphene-3.0b5.dist-info/top_level.txt
jetblack_graphene-3.0b5.dist-info/RECORD
